kvell_pdf/__init__.py
kvell_pdf/main.py
kvell_pdf/utils.py
kvell_pdf-0.0.2.dist-info/METADATA
kvell_pdf-0.0.2.dist-info/WHEEL
kvell_pdf-0.0.2.dist-info/entry_points.txt
kvell_pdf-0.0.2.dist-info/top_level.txt
kvell_pdf-0.0.2.dist-info/RECORD
